whitehat/__init__.py
whitehat/browser.py
whitehat/bruteforce.py
whitehat/cryptography.py
whitehat/ddos.py
whitehat/errors.py
whitehat/ip.py
whitehat/keylogger.py
whitehat/phonenumber.py
whitehat/port.py
whitehat/reverse_shell.py
whitehat/wifi.py
whitehat/cryptography_functions/__init__.py
whitehat/cryptography_functions/binary.py
whitehat/cryptography_functions/caesar_cipher.py
whitehat/cryptography_functions/morse.py
whitehat/cryptography_functions/vigenere_cipher.py
whitehat/utilities/__init__.py
whitehat/utilities/ddos_utils.py
whitehat-1.2.3.dist-info/LICENSE
whitehat-1.2.3.dist-info/METADATA
whitehat-1.2.3.dist-info/WHEEL
whitehat-1.2.3.dist-info/top_level.txt
whitehat-1.2.3.dist-info/RECORD
