Metadata-Version: 2.1
Name: whitehat
Version: 1.2.3
Summary: Python Packages For Ethical Hacking
Home-page: https://github.com/EterNomm/Whitehat
Author: LyQuid
Author-email: lyquidpersonal@gmail.com
License: Apache License 2.0
Project-URL: Source Code, https://github.com/EterNomm/Whitehat
Project-URL: Discord, https://discord.gg/qpT2AeYZRN
Project-URL: Issue tracker, https://github.com/EterNomm/Whitehat/issues
Keywords: python,hacking,whitehat,hacking tool,ethical hacking
Platform: UNKNOWN
Classifier: Development Status :: 5 - Production/Stable
Classifier: Intended Audience :: Science/Research
Classifier: Programming Language :: Python :: 3.7
Classifier: Programming Language :: Python :: 3.8
Classifier: Programming Language :: Python :: 3.9
Classifier: Programming Language :: Python :: 3.10
Classifier: License :: OSI Approved :: Apache Software License
Classifier: Operating System :: Android
Classifier: Operating System :: Microsoft :: Windows
Classifier: Operating System :: MacOS
Classifier: Operating System :: POSIX :: Linux
License-File: LICENSE
Requires-Dist: python-socketio (==5.4.1)
Requires-Dist: phonenumbers (==8.12.36)
Requires-Dist: tqdm
Requires-Dist: pynput (==1.7.4)
